mopidycli
