Metadata-Version: 1.1
Name: MopidyCLI
Version: 0.2.0
Summary: Mopidy tool controlling playback from command line
Home-page: https://github.com/havardgulldahl/mopidycli
Author: Håvard Gulldahl
Author-email: havard@gulldahl.no
License: Apache License, Version 2.0
Platform: UNKNOWN
Classifier: Intended Audience :: End Users/Desktop
Classifier: License :: OSI Approved :: Apache Software License
Classifier: Operating System :: OS Independent
Classifier: Programming Language :: Python :: 2
Classifier: Topic :: Multimedia :: Sound/Audio :: Players
